{
  "society": {
    "description": "",
    "color": "var(--green)"
  },
  "technology": {
    "description": "",
    "color": "var(--blue)"
  },
  "life": {
    "description": "",
    "color": "var(--orange)"
  },
  "general": {
    "description": "",
    "color": "var(--red)"
  },
  "highlight": {
    "description": "",
    "color": "var(--accent)"
  },
  "travel": {
    "description": "",
    "color": "var(--yellow)"
  },
  "philosophy": {
    "description": "",
    "color": "var(--blue)"
  },
  "index": {
    "description": "",
    "color": "var(--blue)"
  },
  "science": {
    "description": "",
    "color": "var(--purple)"
  },
  "young-shan": {
    "description": "",
    "color": "var(--green)"
  },
  "prose": {
    "description": "",
    "color": "var(--orange)"
  },
  "design": {
    "description": "",
    "color": "var(--blue)"
  },
  "education": {
      "description": "",
      "color": "var(--blue)"
  },
  "ongoing": {
    "description": "",
    "color": "var(--orange)"
  },
  "projects": {
    "description": "",
    "color": "var(--orange)"
  },
  "startups": {
    "description": "",
    "color": "var(--red)"
  }
}
